sam4onnx/__init__.py
sam4onnx/__main__.py
sam4onnx/onnx_attr_const_modify.py
sam4onnx-1.0.17.dist-info/licenses/LICENSE
sam4onnx-1.0.17.dist-info/METADATA
sam4onnx-1.0.17.dist-info/WHEEL
sam4onnx-1.0.17.dist-info/entry_points.txt
sam4onnx-1.0.17.dist-info/top_level.txt
sam4onnx-1.0.17.dist-info/RECORD
